torch/functional.py
torch/version.py
torch/testing/__init__.py
torch/_utils_internal.py
torch/_torch_docs.py
torch/serialization.py
torch/lib/libcaffe2_detectron_ops.so
torch/lib/THNN.h
torch/lib/libmkldnn.so
torch/lib/libonnxifi_dummy.so
torch/lib/libcaffe2_observers.so
torch/lib/libshm.so
torch/lib/libcaffe2.so
torch/lib/libcaffe2_module_test_dynamic.so
torch/lib/libtorch_python.so
torch/lib/libmkldnn.so.0.14.0
torch/lib/libgomp-7bcb08ae.so.1
torch/lib/libmkldnn.so.0
torch/lib/torch_shm_manager
torch/lib/THCUNN.h
torch/lib/libtorch.so
torch/lib/libonnxifi.so
torch/lib/libtorch.so.1
torch/lib/include/pybind11/chrono.h
torch/lib/include/pybind11/pytypes.h
torch/lib/include/pybind11/eigen.h
torch/lib/include/pybind11/detail/init.h
torch/lib/include/pybind11/detail/common.h
torch/lib/include/pybind11/detail/class.h
torch/lib/include/pybind11/detail/descr.h
torch/lib/include/pybind11/detail/internals.h
torch/lib/include/pybind11/detail/typeid.h
torch/lib/include/pybind11/eval.h
torch/lib/include/pybind11/options.h
torch/lib/include/pybind11/iostream.h
torch/lib/include/pybind11/embed.h
torch/lib/include/pybind11/attr.h
torch/lib/include/pybind11/buffer_info.h
torch/lib/include/pybind11/functional.h
torch/lib/include/pybind11/common.h
torch/lib/include/pybind11/pybind11.h
torch/lib/include/pybind11/stl_bind.h
torch/lib/include/pybind11/stl.h
torch/lib/include/pybind11/numpy.h
torch/lib/include/pybind11/cast.h
torch/lib/include/pybind11/operators.h
torch/lib/include/pybind11/complex.h
torch/lib/include/torch/extension.h
torch/lib/include/torch/script.h
torch/lib/include/torch/csrc/THP_export.h
torch/lib/include/torch/csrc/Module.h
torch/lib/include/torch/csrc/DataLoader.h
torch/lib/include/torch/csrc/WindowsTorchApiMacro.h
torch/lib/include/torch/csrc/PythonTypes.h
torch/lib/include/torch/csrc/serialization.h
torch/lib/include/torch/csrc/StorageDefs.h
torch/lib/include/torch/csrc/Dtype.h
torch/lib/include/torch/csrc/PtrWrapper.h
torch_u2net-1.0.0.dist-info/WHEEL
torch_u2net-1.0.0.dist-info/RECORD
torch_u2net-1.0.0.dist-info/top_level.txt
torch_u2net-1.0.0.dist-info/entry_points.txt
torch_u2net-1.0.0.dist-info/METADATA
