Metadata-Version: 2.1
Name: torch_u2net
Version: 1.0.0
Summary: Tensors and Dynamic neural networks in Python with strong GPU acceleration
Home-page: UNKNOWN
Author: UNKNOWN
Author-email: UNKNOWN
License: UNKNOWN
Platform: UNKNOWN
